swh/provenance/__init__.py
swh/provenance/cli.py
swh/provenance/exc.py
swh/provenance/grpc_client.py
swh/provenance/grpc_server.py
swh/provenance/interface.py
swh/provenance/luigi.py
swh/provenance/py.typed
swh/provenance/pytest_plugin.py
swh/provenance/shell.py
swh/provenance/api/client.py
swh/provenance/api/serializers.py
swh/provenance/api/server.py
swh/provenance/backend/graph.py
swh/provenance/backend/known_swhid_proxy.py
swh/provenance/backend/postgresql.py
swh/provenance/grpc/swhprovenance.proto
swh/provenance/grpc/swhprovenance_pb2.py
swh/provenance/grpc/swhprovenance_pb2.pyi
swh/provenance/grpc/swhprovenance_pb2_grpc.py
swh/provenance/sql/30-schema.sql
swh/provenance/sql/60-indexes.sql
swh/provenance/tests/__init__.py
swh/provenance/tests/provenance_tests.py
swh/provenance/tests/test_grpc.py
swh/provenance/tests/test_grpc_client.py
swh/provenance/tests/test_luigi.py
swh/provenance/tests/test_provenance.py
swh/provenance/tests/test_provenance_graph.py
swh/provenance/tests/test_provenance_known_swhid_proxy.py
swh/provenance/tests/test_provenance_remote.py
swh_provenance-0.4.2.dist-info/licenses/AUTHORS
swh_provenance-0.4.2.dist-info/licenses/LICENSE
swh_provenance-0.4.2.dist-info/METADATA
swh_provenance-0.4.2.dist-info/WHEEL
swh_provenance-0.4.2.dist-info/entry_points.txt
swh_provenance-0.4.2.dist-info/top_level.txt
swh_provenance-0.4.2.dist-info/RECORD
